cmip_basins/__init__.py
cmip_basins/basins.py
cmip_basins/cmip6.py
cmip_basins/gfdl.py
cmip_basins-1.0.5.data/scripts/basins.py
cmip_basins-1.0.5.dist-info/METADATA
cmip_basins-1.0.5.dist-info/WHEEL
cmip_basins-1.0.5.dist-info/top_level.txt
cmip_basins-1.0.5.dist-info/RECORD
