Metadata-Version: 2.1
Name: cmip-basins
Version: 1.0.5
Summary: Generate CMIP-style ocean basin masks
Home-page: https://github.com/jkrasting/cmip_basins
Author: John Krasting
Author-email: john.krasting@noaa.gov
License: UNKNOWN
Keywords: cmip cmip6 omip oceanography
Platform: UNKNOWN
Classifier: Development Status :: 5 - Production/Stable
Classifier: Intended Audience :: Science/Research
Classifier: Topic :: Scientific/Engineering
Classifier: License :: Public Domain
Classifier: Programming Language :: Python :: 3.7
Classifier: Programming Language :: Python :: 3.8
Classifier: Programming Language :: Python :: 3.9
Requires-Python: >=3.7
Requires-Dist: numpy (>=1.17)
Requires-Dist: xarray (>=0.16.0)
